dsnd3756_probability/Binomialdistribution.py
dsnd3756_probability/Gaussiandistribution.py
dsnd3756_probability/Generaldistribution.py
dsnd3756_probability/__init__.py
dsnd3756_probability-1.3756.dist-info/METADATA
dsnd3756_probability-1.3756.dist-info/WHEEL
dsnd3756_probability-1.3756.dist-info/top_level.txt
dsnd3756_probability-1.3756.dist-info/RECORD
