Metadata-Version: 2.1
Name: dsnd3756-probability
Version: 1.3756
Summary: Gaussian and Binomial distributions
Home-page: UNKNOWN
Author: Carlos A., Andrew Paster
Author-email: karlovski@live.com
License: UNKNOWN
Platform: UNKNOWN
